bcm/__init__.py
bcm/cloister.py
bcm/galaxy.py
bcm/version.py
bcm/photos/0.jpg
bcm/photos/1.jpg
bcm/photos/10.jpg
bcm/photos/100.jpg
bcm/photos/101.jpg
bcm/photos/102.jpg
bcm/photos/103.jpg
bcm/photos/104.jpg
bcm/photos/105.jpg
bcm/photos/106.jpg
bcm/photos/107.jpg
bcm/photos/108.jpg
bcm/photos/109.jpg
bcm/photos/11.jpg
bcm/photos/110.jpg
bcm/photos/111.jpg
bcm/photos/112.jpg
bcm/photos/113.jpg
bcm/photos/114.jpg
bcm/photos/115.jpg
bcm/photos/116.jpg
bcm/photos/117.jpg
bcm/photos/118.jpg
bcm/photos/119.jpg
bcm/photos/12.jpg
bcm/photos/120.jpg
bcm/photos/121.jpg
bcm/photos/122.jpg
bcm/photos/123.jpg
bcm/photos/124.jpg
bcm/photos/125.jpg
bcm/photos/126.jpg
bcm/photos/127.jpg
bcm/photos/128.jpg
bcm/photos/129.jpg
bcm/photos/13.jpg
bcm/photos/130.jpg
bcm/photos/131.jpg
bcm/photos/132.jpg
bcm/photos/133.jpg
bcm/photos/134.jpg
bcm/photos/135.jpg
bcm/photos/136.jpg
bcm/photos/137.jpg
bcm/photos/138.jpg
bcm/photos/139.jpg
bcm/photos/14.jpg
bcm/photos/140.jpg
bcm/photos/141.jpg
bcm/photos/142.jpg
bcm/photos/143.jpg
bcm/photos/144.jpg
bcm/photos/145.jpg
bcm/photos/146.jpg
bcm/photos/147.jpg
bcm/photos/148.jpg
bcm/photos/149.jpg
bcm/photos/15.jpg
bcm/photos/150.jpg
bcm/photos/151.jpg
bcm/photos/152.jpg
bcm/photos/153.jpg
bcm/photos/154.jpg
bcm/photos/155.jpg
bcm/photos/156.jpg
bcm/photos/157.jpg
bcm/photos/158.jpg
bcm/photos/159.jpg
bcm/photos/16.jpg
bcm/photos/160.jpg
bcm/photos/161.jpg
bcm/photos/162.jpg
bcm/photos/163.jpg
bcm/photos/164.jpg
bcm/photos/165.jpg
bcm/photos/166.jpg
bcm/photos/167.jpg
bcm/photos/168.jpg
bcm/photos/169.jpg
bcm/photos/17.jpg
bcm/photos/170.jpg
bcm/photos/171.jpg
bcm/photos/172.jpg
bcm/photos/173.jpg
bcm/photos/174.jpg
bcm/photos/175.jpg
bcm/photos/176.jpg
bcm/photos/177.jpg
bcm/photos/178.jpg
bcm/photos/179.jpg
bcm/photos/18.jpg
bcm/photos/180.jpg
bcm/photos/181.jpg
bcm/photos/182.jpg
bcm/photos/183.jpg
bcm/photos/184.jpg
bcm/photos/185.jpg
bcm/photos/186.jpg
bcm/photos/187.jpg
bcm/photos/188.jpg
bcm/photos/189.jpg
bcm/photos/19.jpg
bcm-0.1.8.1.dist-info/METADATA
bcm-0.1.8.1.dist-info/WHEEL
bcm-0.1.8.1.dist-info/top_level.txt
bcm-0.1.8.1.dist-info/RECORD
