Metadata-Version: 2.1
Name: bcm
Version: 0.1.8.1
Summary: This is a kid's python library.
Home-page: https://shequ.codemao.cn/course
Author: codemao
Author-email: zhangfayao@codemao.cn
License: GPL2
Platform: UNKNOWN
Requires-Python: >=3.6
Requires-Dist: vpython (==7.6.1)
Requires-Dist: argon2-cffi (==19.2.0)
Requires-Dist: cryptography (==3.2.1)
Requires-Dist: pygame (==1.9.6)
